markdown_code_runner.py
markdown_code_runner-2.7.0.dist-info/licenses/LICENSE
markdown_code_runner-2.7.0.dist-info/METADATA
markdown_code_runner-2.7.0.dist-info/WHEEL
markdown_code_runner-2.7.0.dist-info/entry_points.txt
markdown_code_runner-2.7.0.dist-info/top_level.txt
markdown_code_runner-2.7.0.dist-info/RECORD
