Metadata-Version: 2.4
Name: markdown-code-runner
Version: 2.7.0
Summary: Automatically execute code blocks within a Markdown file and update the output in-place
Author-email: Bas Nijholt <bas@nijho.lt>
Project-URL: Homepage, https://github.com/basnijholt/markdown-code-runner
Project-URL: Documentation, https://markdown-code-runner.nijho.lt
Classifier: Programming Language :: Python :: 3
Classifier: Programming Language :: Python :: 3.9
Classifier: Programming Language :: Python :: 3.10
Classifier: Programming Language :: Python :: 3.11
Classifier: Programming Language :: Python :: 3.12
Classifier: Programming Language :: Python :: 3.13
Classifier: Programming Language :: Python :: 3.14
Classifier: License :: OSI Approved :: MIT License
Classifier: Operating System :: OS Independent
Requires-Python: >=3.9
License-File: LICENSE
Provides-Extra: test
Requires-Dist: pytest; extra == "test"
Requires-Dist: pre-commit; extra == "test"
Requires-Dist: coverage; extra == "test"
Requires-Dist: pytest-cov; extra == "test"
Provides-Extra: docs
Requires-Dist: zensical; extra == "docs"
Requires-Dist: markdown-gfm-admonition; extra == "docs"
Requires-Dist: pandas; extra == "docs"
Requires-Dist: tabulate; extra == "docs"
Requires-Dist: requests; extra == "docs"
Dynamic: license-file
